LICENSE
MANIFEST.in
README.md
pyproject.toml
setup.cfg
setup.py
versioneer.py
./docs/conf.py
./netspec/__init__.py
./netspec/_version.py
./netspec/emulator.py
./netspec/netspec.py
./netspec/data/log_theme.ini
./netspec/io/__init__.py
./netspec/test/conftest.py
./netspec/test/test_basic.py
./netspec/training/__init__.py
./netspec/training/optimizer.py
./netspec/training/training_data_tools.py
./netspec/training/training_model.py
./netspec/utils/__init__.py
./netspec/utils/autoencoder.py
./netspec/utils/configuration.py
./netspec/utils/custom_activation.py
./netspec/utils/custom_metrics.py
./netspec/utils/data_utils.py
./netspec/utils/file_utils.py
./netspec/utils/hdf5_utils.py
./netspec/utils/logging.py
./netspec/utils/model_utils.py
./netspec/utils/package_data.py
netspec/_version.py
netspec.egg-info/PKG-INFO
netspec.egg-info/SOURCES.txt
netspec.egg-info/dependency_links.txt
netspec.egg-info/requires.txt
netspec.egg-info/top_level.txt
netspec/data/log_theme.ini